stockdatascrape/__init__.py
stockdatascrape/financialdata.py
stockdatascrape/pricedata.py
nsestockdata-0.2.dist-info/LICENSE
nsestockdata-0.2.dist-info/METADATA
nsestockdata-0.2.dist-info/WHEEL
nsestockdata-0.2.dist-info/top_level.txt
nsestockdata-0.2.dist-info/RECORD
