Metadata-Version: 2.1
Name: nsestockdata
Version: 0.2
Summary: A python package to get NSE stock data.
Home-page: https://github.com/Vikram-Ahuja/nsestockdata.git
Author: Vikram Ahuja
Author-email: vikramahuja1313@gmail.com
License: UNKNOWN
Platform: UNKNOWN
Classifier: Programming Language :: Python :: 3
Classifier: License :: OSI Approved :: MIT License
Classifier: Operating System :: OS Independent
Requires-Python: >=3.6
